README.txt
setup.py
villagereach/__init__.py
villagereach/file_transfer.py
villagereach.egg-info/PKG-INFO
villagereach.egg-info/SOURCES.txt
villagereach.egg-info/dependency_links.txt
villagereach.egg-info/requires.txt
villagereach.egg-info/top_level.txt
villagereach/test/__init__.py