Metadata-Version: 1.0
Name: villagereach
Version: 0.0.6
Summary: Facilitating bluetooth file transfer
Home-page: http://pypi.python.org/pypi/VillageReach/
Author: D4D
Author-email: leohentschker@college.harvard.edu
License: LICENSE.txt
Platform: UNKNOWN
